oddagent/README.en.md
oddagent/README.md
oddagent/__init__.py
oddagent/app.py
oddagent/config_loader.py
oddagent/odd_agent_config - 副本.json
oddagent/odd_agent_config.json
oddagent/odd_agent_logger.py
oddagent/requirements.txt
oddagent/docs/full_api_doc.md
oddagent/docs/mcp_protocol.md
oddagent/logic/__init__.py
oddagent/logic/api_request_composer.py
oddagent/logic/api_response_paser.py
oddagent/logic/odd_agent.py
oddagent/logic/odd_agent_error.py
oddagent/logic/schedule_task.py
oddagent/modules/__init__.py
oddagent/modules/generate_testset.py
oddagent/modules/module_tool.py
oddagent/modules/xiaoluo/__init__.py
oddagent/modules/xiaoluo/conference_config.json
oddagent/router/__init__.py
oddagent/router/tools_api.py
oddagent/router/tools_api_mcp.py
oddagent/router/tools_front.py
oddagent/router/tools_front_markit.py
oddagent/static/bootstrap.min.css
oddagent/static/bootstrap.min.js
oddagent/static/jquery.slim.min.js
oddagent/static/login.html
oddagent/static/popper.min.js
oddagent/static/xlsx.core.min.js
oddagent/static/common/crypto-js.js
oddagent/static/common/oddagent.js
oddagent/static/common/oddasr.js
oddagent/static/common/oddrecoder.js
oddagent/static/common/css/hotwords.css
oddagent/static/common/css/iconfont.css
oddagent/static/common/css/user_pwd.css
oddagent/static/common/css/images/all2.png
oddagent/static/common/css/images/capitals-tip.png
oddagent/static/common/css/images/myicon.png
oddagent/static/common/css/images/setting.png
oddagent/static/common/css/images/sprite_all.png
oddagent/static/common/js/hotwords.js
oddagent/static/common/js/user_pwd.js
oddagent/static/dist/css/adminlte.css
oddagent/static/dist/css/adminlte.min.css
oddagent/static/dist/css/alt/adminlte.components.css
oddagent/static/dist/css/alt/adminlte.components.min.css
oddagent/static/dist/css/alt/adminlte.core.css
oddagent/static/dist/css/alt/adminlte.core.min.css
oddagent/static/dist/css/alt/adminlte.extra-components.css
oddagent/static/dist/css/alt/adminlte.extra-components.min.css
oddagent-1.2.30.dist-info/licenses/LICENSE
oddagent-1.2.30.dist-info/METADATA
oddagent-1.2.30.dist-info/WHEEL
oddagent-1.2.30.dist-info/entry_points.txt
oddagent-1.2.30.dist-info/top_level.txt
oddagent-1.2.30.dist-info/RECORD
