Metadata-Version: 2.4
Name: oddagent
Version: 1.2.30
Summary: A General-Purpose Intent and Command Recognition Framework
Author-email: Catherine Wei <catherine@oddmeta.com>, Jacky Wei <jacky@oddmeta.com>
License-Expression: MIT
Project-URL: Homepage, https://oddmeta.net/oddagent
Project-URL: Repository, https://github.com/oddmeta/oddagent
Project-URL: Issues, https://github.com/oddmeta/oddagent/issues
Classifier: Programming Language :: Python :: 3
Classifier: Operating System :: OS Independent
Requires-Python: >=3.10
License-File: LICENSE
Requires-Dist: Flask
Requires-Dist: requests
Requires-Dist: Werkzeug
Requires-Dist: flask_cors
Requires-Dist: python-dotenv
Dynamic: license-file
